pymdown_env/__init__.py
pymdown_env/envpreprocessor.py
pymdown_env-1.0.1.dist-info/LICENSE.md
pymdown_env-1.0.1.dist-info/METADATA
pymdown_env-1.0.1.dist-info/WHEEL
pymdown_env-1.0.1.dist-info/top_level.txt
pymdown_env-1.0.1.dist-info/RECORD
