Metadata-Version: 2.1
Name: pymdown-env
Version: 1.0.1
Summary: pymdown extension to inline replace environment variables
Home-page: https://github.com/skirsten/pymdown-env
Author: Simon Kirsten
Author-email: simon.kirsten@stud.h-da.de
License: MIT
Platform: UNKNOWN
Classifier: Programming Language :: Python :: 3
Classifier: License :: OSI Approved :: MIT License
Classifier: Operating System :: OS Independent
Requires-Python: >=3.4
